jaxonlayers/__init__.py
jaxonlayers/functions/__init__.py
jaxonlayers/functions/attention.py
jaxonlayers/functions/embedding.py
jaxonlayers/functions/initialization.py
jaxonlayers/functions/masking.py
jaxonlayers/functions/normalization.py
jaxonlayers/functions/regularization.py
jaxonlayers/functions/state_space.py
jaxonlayers/functions/utils.py
jaxonlayers/layers/__init__.py
jaxonlayers/layers/abstract.py
jaxonlayers/layers/attention.py
jaxonlayers/layers/convolution.py
jaxonlayers/layers/normalization.py
jaxonlayers/layers/regularization.py
jaxonlayers/layers/sequential.py
jaxonlayers/layers/state_space.py
jaxonlayers/layers/transformer.py
jaxonlayers-0.2.1.dist-info/METADATA
jaxonlayers-0.2.1.dist-info/WHEEL
jaxonlayers-0.2.1.dist-info/RECORD
