Metadata-Version: 2.4
Name: jaxonlayers
Version: 0.2.1
Summary: Additional layers and functions that extend Equinox
Requires-Python: >=3.13
Requires-Dist: beartype>=0.21.0
Requires-Dist: equinox>=0.13.0
Requires-Dist: jax>=0.8.0
Requires-Dist: jaxtyping>=0.3.2
